setup.py
gdbwrap/__init__.py
gdbwrap/gdbwrap.py
gdbwrap.egg-info/PKG-INFO
gdbwrap.egg-info/SOURCES.txt
gdbwrap.egg-info/dependency_links.txt
gdbwrap.egg-info/requires.txt
gdbwrap.egg-info/top_level.txt