Metadata-Version: 1.0
Name: gdbwrap
Version: 0.0.2
Summary: Wrapper for graph database queries.
Home-page: https://github.com/danielcouch/gdbwrap
Author: Daniel Couch
Author-email: danielcouch1864@gmail.com
License: MIT
Platform: UNKNOWN
